{
  "total_count": 1,
  "workflow_runs": [
    {
      "id": 28333714244,
      "name": "Build Windows Release",
      "node_id": "WFR_kwLOTH2z9s8AAAAGmNIrRA",
      "head_branch": "master",
      "head_sha": "2e1801b9f75c58a5fbc39fc6bf2d6c72a226062a",
      "path": ".github/workflows/build-windows.yml",
      "display_title": "Build Windows Release",
      "run_number": 1,
      "event": "workflow_dispatch",
      "status": "completed",
      "conclusion": "failure",
      "workflow_id": 303699121,
      "check_suite_id": 76489034239,
      "check_suite_node_id": "CS_kwDOTH2z9s8AAAARzxoJ_w",
      "url": "https://api.github.com/repos/Vim-01/vimozz/actions/runs/28333714244",
      "html_url": "https://github.com/Vim-01/vimozz/actions/runs/28333714244",
      "pull_requests": [

      ],
      "created_at": "2026-06-28T19:39:44Z",
      "updated_at": "2026-06-28T19:42:36Z",
      "actor": {
        "login": "Vim-01",
        "id": 239149985,
        "node_id": "U_kgDODkEjoQ",
        "avatar_url": "https://avatars.githubusercontent.com/u/239149985?v=4",
        "gravatar_id": "",
        "url": "https://api.github.com/users/Vim-01",
        "html_url": "https://github.com/Vim-01",
        "followers_url": "https://api.github.com/users/Vim-01/followers",
        "following_url": "https://api.github.com/users/Vim-01/following{/other_user}",
        "gists_url": "https://api.github.com/users/Vim-01/gists{/gist_id}",
        "starred_url": "https://api.github.com/users/Vim-01/starred{/owner}{/repo}",
        "subscriptions_url": "https://api.github.com/users/Vim-01/subscriptions",
        "organizations_url": "https://api.github.com/users/Vim-01/orgs",
        "repos_url": "https://api.github.com/users/Vim-01/repos",
        "events_url": "https://api.github.com/users/Vim-01/events{/privacy}",
        "received_events_url": "https://api.github.com/users/Vim-01/received_events",
        "type": "User",
        "user_view_type": "public",
        "site_admin": false
      },
      "run_attempt": 1,
      "referenced_workflows": [

      ],
      "run_started_at": "2026-06-28T19:39:44Z",
      "triggering_actor": {
        "login": "Vim-01",
        "id": 239149985,
        "node_id": "U_kgDODkEjoQ",
        "avatar_url": "https://avatars.githubusercontent.com/u/239149985?v=4",
        "gravatar_id": "",
        "url": "https://api.github.com/users/Vim-01",
        "html_url": "https://github.com/Vim-01",
        "followers_url": "https://api.github.com/users/Vim-01/followers",
        "following_url": "https://api.github.com/users/Vim-01/following{/other_user}",
        "gists_url": "https://api.github.com/users/Vim-01/gists{/gist_id}",
        "starred_url": "https://api.github.com/users/Vim-01/starred{/owner}{/repo}",
        "subscriptions_url": "https://api.github.com/users/Vim-01/subscriptions",
        "organizations_url": "https://api.github.com/users/Vim-01/orgs",
        "repos_url": "https://api.github.com/users/Vim-01/repos",
        "events_url": "https://api.github.com/users/Vim-01/events{/privacy}",
        "received_events_url": "https://api.github.com/users/Vim-01/received_events",
        "type": "User",
        "user_view_type": "public",
        "site_admin": false
      },
      "jobs_url": "https://api.github.com/repos/Vim-01/vimozz/actions/runs/28333714244/jobs",
      "logs_url": "https://api.github.com/repos/Vim-01/vimozz/actions/runs/28333714244/logs",
      "check_suite_url": "https://api.github.com/repos/Vim-01/vimozz/check-suites/76489034239",
      "artifacts_url": "https://api.github.com/repos/Vim-01/vimozz/actions/runs/28333714244/artifacts",
      "cancel_url": "https://api.github.com/repos/Vim-01/vimozz/actions/runs/28333714244/cancel",
      "rerun_url": "https://api.github.com/repos/Vim-01/vimozz/actions/runs/28333714244/rerun",
      "previous_attempt_url": null,
      "workflow_url": "https://api.github.com/repos/Vim-01/vimozz/actions/workflows/303699121",
      "head_commit": {
        "id": "2e1801b9f75c58a5fbc39fc6bf2d6c72a226062a",
        "tree_id": "3b9b416df92e23e8b39cb52f940da6a408835901",
        "message": "Add GitHub Actions workflow to build Windows exe and attach to release",
        "timestamp": "2026-06-28T19:39:35Z",
        "author": {
          "name": "vim",
          "email": "vim@example.com"
        },
        "committer": {
          "name": "vim",
          "email": "vim@example.com"
        }
      },
      "repository": {
        "id": 1283306486,
        "node_id": "R_kgDOTH2z9g",
        "name": "vimozz",
        "full_name": "Vim-01/vimozz",
        "private": false,
        "owner": {
          "login": "Vim-01",
          "id": 239149985,
          "node_id": "U_kgDODkEjoQ",
          "avatar_url": "https://avatars.githubusercontent.com/u/239149985?v=4",
          "gravatar_id": "",
          "url": "https://api.github.com/users/Vim-01",
          "html_url": "https://github.com/Vim-01",
          "followers_url": "https://api.github.com/users/Vim-01/followers",
          "following_url": "https://api.github.com/users/Vim-01/following{/other_user}",
          "gists_url": "https://api.github.com/users/Vim-01/gists{/gist_id}",
          "starred_url": "https://api.github.com/users/Vim-01/starred{/owner}{/repo}",
          "subscriptions_url": "https://api.github.com/users/Vim-01/subscriptions",
          "organizations_url": "https://api.github.com/users/Vim-01/orgs",
          "repos_url": "https://api.github.com/users/Vim-01/repos",
          "events_url": "https://api.github.com/users/Vim-01/events{/privacy}",
          "received_events_url": "https://api.github.com/users/Vim-01/received_events",
          "type": "User",
          "user_view_type": "public",
          "site_admin": false
        },
        "html_url": "https://github.com/Vim-01/vimozz",
        "description": "Vimozz - Twitch Music Bot with YouTube integration and anti-censorship bypass",
        "fork": false,
        "url": "https://api.github.com/repos/Vim-01/vimozz",
        "forks_url": "https://api.github.com/repos/Vim-01/vimozz/forks",
        "keys_url": "https://api.github.com/repos/Vim-01/vimozz/keys{/key_id}",
        "collaborators_url": "https://api.github.com/repos/Vim-01/vimozz/collaborators{/collaborator}",
        "teams_url": "https://api.github.com/repos/Vim-01/vimozz/teams",
        "hooks_url": "https://api.github.com/repos/Vim-01/vimozz/hooks",
        "issue_events_url": "https://api.github.com/repos/Vim-01/vimozz/issues/events{/number}",
        "events_url": "https://api.github.com/repos/Vim-01/vimozz/events",
        "assignees_url": "https://api.github.com/repos/Vim-01/vimozz/assignees{/user}",
        "branches_url": "https://api.github.com/repos/Vim-01/vimozz/branches{/branch}",
        "tags_url": "https://api.github.com/repos/Vim-01/vimozz/tags",
        "blobs_url": "https://api.github.com/repos/Vim-01/vimozz/git/blobs{/sha}",
        "git_tags_url": "https://api.github.com/repos/Vim-01/vimozz/git/tags{/sha}",
        "git_refs_url": "https://api.github.com/repos/Vim-01/vimozz/git/refs{/sha}",
        "trees_url": "https://api.github.com/repos/Vim-01/vimozz/git/trees{/sha}",
        "statuses_url": "https://api.github.com/repos/Vim-01/vimozz/statuses/{sha}",
        "languages_url": "https://api.github.com/repos/Vim-01/vimozz/languages",
        "stargazers_url": "https://api.github.com/repos/Vim-01/vimozz/stargazers",
        "contributors_url": "https://api.github.com/repos/Vim-01/vimozz/contributors",
        "subscribers_url": "https://api.github.com/repos/Vim-01/vimozz/subscribers",
        "subscription_url": "https://api.github.com/repos/Vim-01/vimozz/subscription",
        "commits_url": "https://api.github.com/repos/Vim-01/vimozz/commits{/sha}",
        "git_commits_url": "https://api.github.com/repos/Vim-01/vimozz/git/commits{/sha}",
        "comments_url": "https://api.github.com/repos/Vim-01/vimozz/comments{/number}",
        "issue_comment_url": "https://api.github.com/repos/Vim-01/vimozz/issues/comments{/number}",
        "contents_url": "https://api.github.com/repos/Vim-01/vimozz/contents/{+path}",
        "compare_url": "https://api.github.com/repos/Vim-01/vimozz/compare/{base}...{head}",
        "merges_url": "https://api.github.com/repos/Vim-01/vimozz/merges",
        "archive_url": "https://api.github.com/repos/Vim-01/vimozz/{archive_format}{/ref}",
        "downloads_url": "https://api.github.com/repos/Vim-01/vimozz/downloads",
        "issues_url": "https://api.github.com/repos/Vim-01/vimozz/issues{/number}",
        "pulls_url": "https://api.github.com/repos/Vim-01/vimozz/pulls{/number}",
        "milestones_url": "https://api.github.com/repos/Vim-01/vimozz/milestones{/number}",
        "notifications_url": "https://api.github.com/repos/Vim-01/vimozz/notifications{?since,all,participating}",
        "labels_url": "https://api.github.com/repos/Vim-01/vimozz/labels{/name}",
        "releases_url": "https://api.github.com/repos/Vim-01/vimozz/releases{/id}",
        "deployments_url": "https://api.github.com/repos/Vim-01/vimozz/deployments"
      },
      "head_repository": {
        "id": 1283306486,
        "node_id": "R_kgDOTH2z9g",
        "name": "vimozz",
        "full_name": "Vim-01/vimozz",
        "private": false,
        "owner": {
          "login": "Vim-01",
          "id": 239149985,
          "node_id": "U_kgDODkEjoQ",
          "avatar_url": "https://avatars.githubusercontent.com/u/239149985?v=4",
          "gravatar_id": "",
          "url": "https://api.github.com/users/Vim-01",
          "html_url": "https://github.com/Vim-01",
          "followers_url": "https://api.github.com/users/Vim-01/followers",
          "following_url": "https://api.github.com/users/Vim-01/following{/other_user}",
          "gists_url": "https://api.github.com/users/Vim-01/gists{/gist_id}",
          "starred_url": "https://api.github.com/users/Vim-01/starred{/owner}{/repo}",
          "subscriptions_url": "https://api.github.com/users/Vim-01/subscriptions",
          "organizations_url": "https://api.github.com/users/Vim-01/orgs",
          "repos_url": "https://api.github.com/users/Vim-01/repos",
          "events_url": "https://api.github.com/users/Vim-01/events{/privacy}",
          "received_events_url": "https://api.github.com/users/Vim-01/received_events",
          "type": "User",
          "user_view_type": "public",
          "site_admin": false
        },
        "html_url": "https://github.com/Vim-01/vimozz",
        "description": "Vimozz - Twitch Music Bot with YouTube integration and anti-censorship bypass",
        "fork": false,
        "url": "https://api.github.com/repos/Vim-01/vimozz",
        "forks_url": "https://api.github.com/repos/Vim-01/vimozz/forks",
        "keys_url": "https://api.github.com/repos/Vim-01/vimozz/keys{/key_id}",
        "collaborators_url": "https://api.github.com/repos/Vim-01/vimozz/collaborators{/collaborator}",
        "teams_url": "https://api.github.com/repos/Vim-01/vimozz/teams",
        "hooks_url": "https://api.github.com/repos/Vim-01/vimozz/hooks",
        "issue_events_url": "https://api.github.com/repos/Vim-01/vimozz/issues/events{/number}",
        "events_url": "https://api.github.com/repos/Vim-01/vimozz/events",
        "assignees_url": "https://api.github.com/repos/Vim-01/vimozz/assignees{/user}",
        "branches_url": "https://api.github.com/repos/Vim-01/vimozz/branches{/branch}",
        "tags_url": "https://api.github.com/repos/Vim-01/vimozz/tags",
        "blobs_url": "https://api.github.com/repos/Vim-01/vimozz/git/blobs{/sha}",
        "git_tags_url": "https://api.github.com/repos/Vim-01/vimozz/git/tags{/sha}",
        "git_refs_url": "https://api.github.com/repos/Vim-01/vimozz/git/refs{/sha}",
        "trees_url": "https://api.github.com/repos/Vim-01/vimozz/git/trees{/sha}",
        "statuses_url": "https://api.github.com/repos/Vim-01/vimozz/statuses/{sha}",
        "languages_url": "https://api.github.com/repos/Vim-01/vimozz/languages",
        "stargazers_url": "https://api.github.com/repos/Vim-01/vimozz/stargazers",
        "contributors_url": "https://api.github.com/repos/Vim-01/vimozz/contributors",
        "subscribers_url": "https://api.github.com/repos/Vim-01/vimozz/subscribers",
        "subscription_url": "https://api.github.com/repos/Vim-01/vimozz/subscription",
        "commits_url": "https://api.github.com/repos/Vim-01/vimozz/commits{/sha}",
        "git_commits_url": "https://api.github.com/repos/Vim-01/vimozz/git/commits{/sha}",
        "comments_url": "https://api.github.com/repos/Vim-01/vimozz/comments{/number}",
        "issue_comment_url": "https://api.github.com/repos/Vim-01/vimozz/issues/comments{/number}",
        "contents_url": "https://api.github.com/repos/Vim-01/vimozz/contents/{+path}",
        "compare_url": "https://api.github.com/repos/Vim-01/vimozz/compare/{base}...{head}",
        "merges_url": "https://api.github.com/repos/Vim-01/vimozz/merges",
        "archive_url": "https://api.github.com/repos/Vim-01/vimozz/{archive_format}{/ref}",
        "downloads_url": "https://api.github.com/repos/Vim-01/vimozz/downloads",
        "issues_url": "https://api.github.com/repos/Vim-01/vimozz/issues{/number}",
        "pulls_url": "https://api.github.com/repos/Vim-01/vimozz/pulls{/number}",
        "milestones_url": "https://api.github.com/repos/Vim-01/vimozz/milestones{/number}",
        "notifications_url": "https://api.github.com/repos/Vim-01/vimozz/notifications{?since,all,participating}",
        "labels_url": "https://api.github.com/repos/Vim-01/vimozz/labels{/name}",
        "releases_url": "https://api.github.com/repos/Vim-01/vimozz/releases{/id}",
        "deployments_url": "https://api.github.com/repos/Vim-01/vimozz/deployments"
      }
    }
  ]
}
